benchllama/__init__.py
benchllama/__main__.py
benchllama/constants.py
benchllama/data_io/__init__.py
benchllama/data_io/loader.py
benchllama/evaluation/__init__.py
benchllama/evaluation/code_runner.py
benchllama/evaluation/evaluator.py
benchllama/evaluation/runners/__init__.py
benchllama/evaluation/runners/cpp_runner.py
benchllama/evaluation/runners/go_runner.py
benchllama/evaluation/runners/java_runner.py
benchllama/evaluation/runners/javascript_runner.py
benchllama/evaluation/runners/python_runner.py
benchllama/evaluation/runners/utils.py
benchllama/evaluation/score_estimator.py
benchllama/inference/__init__.py
benchllama/inference/model_provider.py
benchllama/inference/prompt_formatter.py
benchllama/logger.py
benchllama/main.py
benchllama/utils.py
benchllama-0.2.7.dist-info/LICENSE
benchllama-0.2.7.dist-info/WHEEL
benchllama-0.2.7.dist-info/entry_points.txt
benchllama-0.2.7.dist-info/METADATA
benchllama-0.2.7.dist-info/RECORD
