Metadata-Version: 2.1
Name: benchllama
Version: 0.2.7
Summary: Benchmark your local LLMs.
Home-page: https://github.com/srikanth235/benchllama/
License: MIT
Keywords: benchmark,llama,ollama,llms,openai,chatgpt,text-generation
Author: Srikanth Srungarapu
Author-email: srikanth235@gmail.com
Requires-Python: >=3.9,<4.0
Classifier: License :: OSI Approved :: MIT License
Classifier: Programming Language :: Python :: 3
Classifier: Programming Language :: Python :: 3.9
Classifier: Programming Language :: Python :: 3.10
Classifier: Programming Language :: Python :: 3.11
Requires-Dist: datasets (>=2.17.0,<3.0.0)
Requires-Dist: joblib (>=1.3.2,<2.0.0)
Requires-Dist: ollama (>=0.1.6,<0.2.0)
Requires-Dist: pandas (>=2.2.0,<3.0.0)
Requires-Dist: typer[all] (>=0.9.0,<0.10.0)
